MasteringPowershellZhongwenbanFix1/README.md
MasteringPowershellZhongwenbanFix1/__init__.py
MasteringPowershellZhongwenbanFix1/__main__.py
MasteringPowershellZhongwenbanFix1/file.epub
MasteringPowershellZhongwenbanFix1/index.html
MasteringPowershellZhongwenbanFix1/css/__init__.py
MasteringPowershellZhongwenbanFix1/css/annotations.css
MasteringPowershellZhongwenbanFix1/css/main.css
MasteringPowershellZhongwenbanFix1/css/normalize.css
MasteringPowershellZhongwenbanFix1/css/popup.css
MasteringPowershellZhongwenbanFix1/font/__init__.py
MasteringPowershellZhongwenbanFix1/font/fontello.eot
MasteringPowershellZhongwenbanFix1/font/fontello.svg
MasteringPowershellZhongwenbanFix1/font/fontello.ttf
MasteringPowershellZhongwenbanFix1/font/fontello.woff
MasteringPowershellZhongwenbanFix1/img/__init__.py
MasteringPowershellZhongwenbanFix1/img/annotator-glyph-sprite.png
MasteringPowershellZhongwenbanFix1/img/annotator-icon-sprite.png
MasteringPowershellZhongwenbanFix1/img/apple-touch-icon.png
MasteringPowershellZhongwenbanFix1/img/cancelfullscreen.png
MasteringPowershellZhongwenbanFix1/img/close.png
MasteringPowershellZhongwenbanFix1/img/fullscreen.png
MasteringPowershellZhongwenbanFix1/img/loader.gif
MasteringPowershellZhongwenbanFix1/img/menu-icon.png
MasteringPowershellZhongwenbanFix1/img/save.png
MasteringPowershellZhongwenbanFix1/img/saved.png
MasteringPowershellZhongwenbanFix1/img/settings-s.png
MasteringPowershellZhongwenbanFix1/img/settings.png
MasteringPowershellZhongwenbanFix1/img/star.png
MasteringPowershellZhongwenbanFix1/js/__init__.py
MasteringPowershellZhongwenbanFix1/js/epub.js
MasteringPowershellZhongwenbanFix1/js/epub.min.js
MasteringPowershellZhongwenbanFix1/js/epub.min.map
MasteringPowershellZhongwenbanFix1/js/hooks.min.js
MasteringPowershellZhongwenbanFix1/js/hooks.min.map
MasteringPowershellZhongwenbanFix1/js/reader.js
MasteringPowershellZhongwenbanFix1/js/reader.js.map
MasteringPowershellZhongwenbanFix1/js/reader.min.js
mastering_powershell_zhongwenban_fix1-2025.3.25.1.dist-info/METADATA
mastering_powershell_zhongwenban_fix1-2025.3.25.1.dist-info/WHEEL
mastering_powershell_zhongwenban_fix1-2025.3.25.1.dist-info/entry_points.txt
mastering_powershell_zhongwenban_fix1-2025.3.25.1.dist-info/top_level.txt
mastering_powershell_zhongwenban_fix1-2025.3.25.1.dist-info/RECORD
